[
  {
    "loser": "Oomph",
    "loserScore": "0",
    "winner": "IMTendo",
    "winnersScore": "2"
  },
  {
    "loser": "Slurm_",
    "loserScore": "0",
    "winner": "Qwizerd",
    "winnersScore": "2"
  },
  {
    "loser": "KONGO | Buffalo",
    "loserScore": "0",
    "winner": "Shimi",
    "winnersScore": "2"
  },
  {
    "loser": "HobbesTheTiger",
    "loserScore": "0",
    "winner": "Yin",
    "winnersScore": "2"
  },
  {
    "loser": "SharpySSJ",
    "loserScore": "0",
    "winner": "IMTendo",
    "winnersScore": "2"
  },
  {
    "loser": "Shimi",
    "loserScore": "1",
    "winner": "Red4Rage",
    "winnersScore": "2"
  },
  {
    "loser": "Qwizerd",
    "loserScore": "1",
    "winner": "GSS_TwE_OaTheRool",
    "winnersScore": "2"
  },
  {
    "loser": "Yin",
    "loserScore": "0",
    "winner": "GREED",
    "winnersScore": "2"
  },
  {
    "loser": "Oomph",
    "loserScore": "0",
    "winner": "Shimi",
    "winnersScore": "2"
  },
  {
    "loser": "Qwizerd",
    "loserScore": "1",
    "winner": "HobbesTheTiger",
    "winnersScore": "2"
  },
  {
    "loser": "KONGO | Buffalo",
    "loserScore": "0",
    "winner": "SharpySSJ",
    "winnersScore": "2"
  },
  {
    "loser": "GREED",
    "loserScore": "1",
    "winner": "Red4Rage",
    "winnersScore": "2"
  },
  {
    "loser": "Slurm_",
    "loserScore": "1",
    "winner": "Yin",
    "winnersScore": "2"
  },
  {
    "loser": "HobbesTheTiger",
    "loserScore": "0",
    "winner": "SharpySSJ",
    "winnersScore": "3"
  },
  {
    "loser": "GSS_TwE_OaTheRool",
    "loserScore": "0",
    "winner": "IMTendo",
    "winnersScore": "3"
  },
  {
    "loser": "Shimi",
    "loserScore": "0",
    "winner": "Yin",
    "winnersScore": "3"
  },
  {
    "loser": "SharpySSJ",
    "loserScore": "0",
    "winner": "GREED",
    "winnersScore": "3"
  },
  {
    "loser": "Red4Rage",
    "loserScore": "0",
    "winner": "IMTendo",
    "winnersScore": "3"
  },
  {
    "loser": "Yin",
    "loserScore": "0",
    "winner": "GSS_TwE_OaTheRool",
    "winnersScore": "3"
  },
  {
    "loser": "GREED",
    "loserScore": "1",
    "winner": "GSS_TwE_OaTheRool",
    "winnersScore": "3"
  },
  {
    "loser": "Red4Rage",
    "loserScore": "2",
    "winner": "IMTendo",
    "winnersScore": "3"
  },
  {
    "loser": "IMTendo",
    "loserScore": "1",
    "winner": "Red4Rage",
    "winnersScore": "3"
  },
  {
    "loser": "GSS_TwE_OaTheRool",
    "loserScore": "2",
    "winner": "Red4Rage",
    "winnersScore": "3"
  }
]